docs/api_reference.md
docs/binds.md
docs/config_files.md
docs/controllers.md
docs/index.md
docs/macros.py
docs/img/edit-binds.png
docs/img/midi-status.png
docs/img/plugins-menu.png
midi_app_controller/__init__.py
midi_app_controller/_version.py
midi_app_controller/config.py
midi_app_controller/napari.yaml
midi_app_controller/utils.py
midi_app_controller/_tests/__init__.py
midi_app_controller/_tests/test_config.py
midi_app_controller/_tests/test_utils.py
midi_app_controller/actions/__init__.py
midi_app_controller/actions/actions_handler.py
midi_app_controller/actions/bound_controller.py
midi_app_controller/actions/napari_actions.py
midi_app_controller/actions/_tests/__init__.py
midi_app_controller/actions/_tests/test_actions_handler.py
midi_app_controller/actions/_tests/test_bound_controller.py
midi_app_controller/actions/_tests/test_napari_actions.py
midi_app_controller/config_files/binds/x_touch_mini_binds.yaml
midi_app_controller/config_files/controllers/x_touch_mini.yaml
midi_app_controller/controller/__init__.py
midi_app_controller/controller/connected_controller.py
midi_app_controller/controller/controller_constants.py
midi_app_controller/controller/_tests/__init__.py
midi_app_controller/controller/_tests/test_connected_controller.py
midi_app_controller/gui/__init__.py
midi_app_controller/gui/binds_editor.py
midi_app_controller/gui/midi_status.py
midi_app_controller/gui/utils.py
midi_app_controller/gui/_tests/__init__.py
midi_app_controller/gui/_tests/test_binds_editor.py
midi_app_controller/gui/_tests/test_midi_status.py
midi_app_controller/models/__init__.py
midi_app_controller/models/app_state.py
midi_app_controller/models/binds.py
midi_app_controller/models/controller.py
midi_app_controller/models/utils.py
midi_app_controller/models/_tests/__init__.py
midi_app_controller/models/_tests/test_binds.py
midi_app_controller/models/_tests/test_controller.py
midi_app_controller/models/_tests/test_utils.py
midi_app_controller/state/__init__.py
midi_app_controller-0.1.1.dist-info/LICENSE
midi_app_controller-0.1.1.dist-info/METADATA
midi_app_controller-0.1.1.dist-info/WHEEL
midi_app_controller-0.1.1.dist-info/entry_points.txt
midi_app_controller-0.1.1.dist-info/top_level.txt
midi_app_controller-0.1.1.dist-info/RECORD
