Metadata-Version: 2.1
Name: midi-app-controller
Version: 0.1.1
Summary: Control napari with a MIDI controller.
Project-URL: Source Code, https://github.com/midi-app-controller/midi-app-controller
Project-URL: Documentation, https://midi-app-controller.readthedocs.io
Classifier: Framework :: napari
Classifier: License :: OSI Approved :: BSD License
Classifier: Programming Language :: Python
Requires-Python: >=3.9
License-File: LICENSE
Requires-Dist: napari>=0.4.19
Requires-Dist: python-rtmidi>=1.5.8
Requires-Dist: pyyaml>=6.0.1
Requires-Dist: pydantic>=2.7.1
Requires-Dist: appdirs>=1.4.4
Requires-Dist: qtpy>=2.4.1
Requires-Dist: superqt>=0.6.5
Provides-Extra: dev
Requires-Dist: midi-app-controller[testing]; extra == "dev"
Requires-Dist: pre-commit>=3.7.0; extra == "dev"
Provides-Extra: testing
Requires-Dist: pytest>=8.2.0; extra == "testing"
Requires-Dist: pytest-cov>=5.0.0; extra == "testing"
Requires-Dist: pytest-qt>=4.0.2; extra == "testing"
Requires-Dist: napari[all]; extra == "testing"
Requires-Dist: flexparser!=0.4.0; extra == "testing"
